funrun/__init__.py
funrun/run.py
ffunrun-0.1.12.dist-info/METADATA
ffunrun-0.1.12.dist-info/WHEEL
ffunrun-0.1.12.dist-info/entry_points.txt
ffunrun-0.1.12.dist-info/top_level.txt
ffunrun-0.1.12.dist-info/RECORD
