Metadata-Version: 2.4
Name: ffunrun
Version: 0.1.12
Summary: funrun
Author-email: niuliangtao <farfarfun@qq.com>
Requires-Python: >=3.8
Requires-Dist: click>=8.1.8
Requires-Dist: funbuild>=1.5.86
Requires-Dist: funutil>=1.0.48
